{
  "version": "mvp_50_v0",
  "source": "curated_public_dev",
  "active_from": "2020-01-01",
  "timestamp_available": "2026-05-04T00:00:00Z",
  "securities": [
    {"ticker": "AAPL", "name": "Apple Inc.", "cik": "0000320193", "exchange": "NASDAQ", "sector": "Information Technology", "industry": "Technology Hardware", "subindustry": "Consumer Electronics", "peers": ["MSFT", "GOOGL", "AMZN", "META", "NVDA"], "exposures": {"broad_usd": 0.75, "rates": 0.50}},
    {"ticker": "MSFT", "name": "Microsoft Corporation", "cik": "0000789019", "exchange": "NASDAQ", "sector": "Information Technology", "industry": "Software", "subindustry": "Systems Software", "peers": ["AAPL", "GOOGL", "AMZN", "META", "ORCL"], "exposures": {"broad_usd": 0.70, "rates": 0.60}},
    {"ticker": "GOOGL", "name": "Alphabet Inc.", "cik": "0001652044", "exchange": "NASDAQ", "sector": "Communication Services", "industry": "Interactive Media", "subindustry": "Internet Services", "peers": ["META", "AMZN", "MSFT", "AAPL", "NFLX"], "exposures": {"broad_usd": 0.65, "rates": 0.55}},
    {"ticker": "AMZN", "name": "Amazon.com, Inc.", "cik": "0001018724", "exchange": "NASDAQ", "sector": "Consumer Discretionary", "industry": "Broadline Retail", "subindustry": "Online Retail", "peers": ["WMT", "COST", "TGT", "HD", "LOW"], "exposures": {"broad_usd": 0.45, "rates": 0.45}},
    {"ticker": "NVDA", "name": "NVIDIA Corporation", "cik": "0001045810", "exchange": "NASDAQ", "sector": "Information Technology", "industry": "Semiconductors", "subindustry": "Semiconductors", "peers": ["AMD", "AVGO", "QCOM", "INTC", "TXN"], "exposures": {"broad_usd": 0.80, "rates": 0.65}},
    {"ticker": "META", "name": "Meta Platforms, Inc.", "cik": "0001326801", "exchange": "NASDAQ", "sector": "Communication Services", "industry": "Interactive Media", "subindustry": "Social Media", "peers": ["GOOGL", "NFLX", "DIS", "MSFT", "AMZN"], "exposures": {"broad_usd": 0.70, "rates": 0.55}},
    {"ticker": "TSLA", "name": "Tesla, Inc.", "cik": "0001318605", "exchange": "NASDAQ", "sector": "Consumer Discretionary", "industry": "Automobiles", "subindustry": "Electric Vehicles", "peers": ["GM", "F", "AMZN", "NVDA", "AAPL"], "exposures": {"broad_usd": 0.60, "rates": 0.70, "credit": 0.35}},
    {"ticker": "BRK.B", "name": "Berkshire Hathaway Inc.", "cik": "0001067983", "exchange": "NYSE", "sector": "Financials", "industry": "Diversified Financials", "subindustry": "Multi-Sector Holdings", "peers": ["JPM", "BAC", "WFC", "GS", "MS"], "exposures": {"rates": 0.70, "credit": 0.45}},
    {"ticker": "JPM", "name": "JPMorgan Chase & Co.", "cik": "0000019617", "exchange": "NYSE", "sector": "Financials", "industry": "Banks", "subindustry": "Diversified Banks", "peers": ["BAC", "WFC", "C", "GS", "MS"], "exposures": {"rates": 0.90, "credit": 0.90}},
    {"ticker": "UNH", "name": "UnitedHealth Group Incorporated", "cik": "0000731766", "exchange": "NYSE", "sector": "Health Care", "industry": "Health Care Providers", "subindustry": "Managed Health Care", "peers": ["ELV", "CI", "HUM", "CVS", "MRK"], "exposures": {"regulatory": 0.85}},
    {"ticker": "LLY", "name": "Eli Lilly and Company", "cik": "0000059478", "exchange": "NYSE", "sector": "Health Care", "industry": "Pharmaceuticals", "subindustry": "Pharmaceuticals", "peers": ["JNJ", "MRK", "PFE", "ABBV", "AMGN"], "exposures": {"regulatory": 0.80, "broad_usd": 0.55}},
    {"ticker": "V", "name": "Visa Inc.", "cik": "0001403161", "exchange": "NYSE", "sector": "Financials", "industry": "Financial Services", "subindustry": "Payments", "peers": ["MA", "AXP", "PYPL", "JPM", "BAC"], "exposures": {"broad_usd": 0.60, "rates": 0.45}},
    {"ticker": "XOM", "name": "Exxon Mobil Corporation", "cik": "0000034088", "exchange": "NYSE", "sector": "Energy", "industry": "Oil Gas & Consumable Fuels", "subindustry": "Integrated Oil & Gas", "peers": ["CVX", "COP", "SLB", "EOG", "MPC"], "exposures": {"wti": 1.0, "natural_gas": 0.65, "broad_usd": 0.60}},
    {"ticker": "AVGO", "name": "Broadcom Inc.", "cik": "0001730168", "exchange": "NASDAQ", "sector": "Information Technology", "industry": "Semiconductors", "subindustry": "Semiconductors", "peers": ["NVDA", "AMD", "QCOM", "TXN", "INTC"], "exposures": {"broad_usd": 0.75, "rates": 0.55}},
    {"ticker": "MA", "name": "Mastercard Incorporated", "cik": "0001141391", "exchange": "NYSE", "sector": "Financials", "industry": "Financial Services", "subindustry": "Payments", "peers": ["V", "AXP", "PYPL", "JPM", "BAC"], "exposures": {"broad_usd": 0.65, "rates": 0.45}},
    {"ticker": "HD", "name": "The Home Depot, Inc.", "cik": "0000354950", "exchange": "NYSE", "sector": "Consumer Discretionary", "industry": "Specialty Retail", "subindustry": "Home Improvement Retail", "peers": ["LOW", "WMT", "COST", "TGT", "AMZN"], "exposures": {"rates": 0.65, "mortgage": 0.75}},
    {"ticker": "PG", "name": "The Procter & Gamble Company", "cik": "0000080424", "exchange": "NYSE", "sector": "Consumer Staples", "industry": "Household Products", "subindustry": "Household Products", "peers": ["KO", "PEP", "WMT", "COST", "MCD"], "exposures": {"broad_usd": 0.60, "inflation": 0.45}},
    {"ticker": "COST", "name": "Costco Wholesale Corporation", "cik": "0000909832", "exchange": "NASDAQ", "sector": "Consumer Staples", "industry": "Consumer Staples Distribution", "subindustry": "Warehouse Clubs", "peers": ["WMT", "TGT", "AMZN", "HD", "LOW"], "exposures": {"inflation": 0.45}},
    {"ticker": "JNJ", "name": "Johnson & Johnson", "cik": "0000200406", "exchange": "NYSE", "sector": "Health Care", "industry": "Pharmaceuticals", "subindustry": "Pharmaceuticals", "peers": ["LLY", "MRK", "PFE", "ABBV", "AMGN"], "exposures": {"regulatory": 0.70, "broad_usd": 0.55}},
    {"ticker": "MRK", "name": "Merck & Co., Inc.", "cik": "0000310158", "exchange": "NYSE", "sector": "Health Care", "industry": "Pharmaceuticals", "subindustry": "Pharmaceuticals", "peers": ["LLY", "JNJ", "PFE", "ABBV", "AMGN"], "exposures": {"regulatory": 0.70, "broad_usd": 0.55}},
    {"ticker": "ABBV", "name": "AbbVie Inc.", "cik": "0001551152", "exchange": "NYSE", "sector": "Health Care", "industry": "Pharmaceuticals", "subindustry": "Pharmaceuticals", "peers": ["LLY", "JNJ", "MRK", "PFE", "AMGN"], "exposures": {"regulatory": 0.70}},
    {"ticker": "CVX", "name": "Chevron Corporation", "cik": "0000093410", "exchange": "NYSE", "sector": "Energy", "industry": "Oil Gas & Consumable Fuels", "subindustry": "Integrated Oil & Gas", "peers": ["XOM", "COP", "SLB", "EOG", "MPC"], "exposures": {"wti": 1.0, "natural_gas": 0.60, "broad_usd": 0.55}},
    {"ticker": "KO", "name": "The Coca-Cola Company", "cik": "0000021344", "exchange": "NYSE", "sector": "Consumer Staples", "industry": "Beverages", "subindustry": "Soft Drinks", "peers": ["PEP", "PG", "MCD", "WMT", "COST"], "exposures": {"broad_usd": 0.70, "inflation": 0.35}},
    {"ticker": "PEP", "name": "PepsiCo, Inc.", "cik": "0000077476", "exchange": "NASDAQ", "sector": "Consumer Staples", "industry": "Beverages", "subindustry": "Soft Drinks", "peers": ["KO", "PG", "MCD", "WMT", "COST"], "exposures": {"broad_usd": 0.65, "inflation": 0.40}},
    {"ticker": "WMT", "name": "Walmart Inc.", "cik": "0000104169", "exchange": "NYSE", "sector": "Consumer Staples", "industry": "Consumer Staples Distribution", "subindustry": "Hypermarkets", "peers": ["COST", "TGT", "AMZN", "HD", "LOW"], "exposures": {"inflation": 0.45}},
    {"ticker": "BAC", "name": "Bank of America Corporation", "cik": "0000070858", "exchange": "NYSE", "sector": "Financials", "industry": "Banks", "subindustry": "Diversified Banks", "peers": ["JPM", "WFC", "C", "GS", "MS"], "exposures": {"rates": 0.90, "credit": 0.90}},
    {"ticker": "WFC", "name": "Wells Fargo & Company", "cik": "0000072971", "exchange": "NYSE", "sector": "Financials", "industry": "Banks", "subindustry": "Diversified Banks", "peers": ["JPM", "BAC", "C", "GS", "MS"], "exposures": {"rates": 0.90, "credit": 0.90}},
    {"ticker": "ORCL", "name": "Oracle Corporation", "cik": "0001341439", "exchange": "NYSE", "sector": "Information Technology", "industry": "Software", "subindustry": "Enterprise Software", "peers": ["MSFT", "CRM", "ADBE", "INTU", "NOW"], "exposures": {"broad_usd": 0.65, "rates": 0.55, "credit": 0.35}},
    {"ticker": "CRM", "name": "Salesforce, Inc.", "cik": "0001108524", "exchange": "NYSE", "sector": "Information Technology", "industry": "Software", "subindustry": "Application Software", "peers": ["MSFT", "ORCL", "ADBE", "INTU", "NOW"], "exposures": {"broad_usd": 0.55, "rates": 0.60}},
    {"ticker": "ADBE", "name": "Adobe Inc.", "cik": "0000796343", "exchange": "NASDAQ", "sector": "Information Technology", "industry": "Software", "subindustry": "Application Software", "peers": ["MSFT", "ORCL", "CRM", "INTU", "NOW"], "exposures": {"broad_usd": 0.60, "rates": 0.60}},
    {"ticker": "NFLX", "name": "Netflix, Inc.", "cik": "0001065280", "exchange": "NASDAQ", "sector": "Communication Services", "industry": "Entertainment", "subindustry": "Streaming", "peers": ["DIS", "GOOGL", "META", "AMZN", "CMCSA"], "exposures": {"broad_usd": 0.55, "rates": 0.55}},
    {"ticker": "DIS", "name": "The Walt Disney Company", "cik": "0001744489", "exchange": "NYSE", "sector": "Communication Services", "industry": "Entertainment", "subindustry": "Movies & Entertainment", "peers": ["NFLX", "CMCSA", "GOOGL", "META", "AMZN"], "exposures": {"broad_usd": 0.45, "rates": 0.50}},
    {"ticker": "CMCSA", "name": "Comcast Corporation", "cik": "0001166691", "exchange": "NASDAQ", "sector": "Communication Services", "industry": "Media", "subindustry": "Cable & Satellite", "peers": ["DIS", "NFLX", "T", "VZ", "TMUS"], "exposures": {"rates": 0.45, "credit": 0.45}},
    {"ticker": "T", "name": "AT&T Inc.", "cik": "0000732717", "exchange": "NYSE", "sector": "Communication Services", "industry": "Telecommunication Services", "subindustry": "Integrated Telecom", "peers": ["VZ", "TMUS", "CMCSA", "DIS", "NFLX"], "exposures": {"rates": 0.55, "credit": 0.70}},
    {"ticker": "VZ", "name": "Verizon Communications Inc.", "cik": "0000732712", "exchange": "NYSE", "sector": "Communication Services", "industry": "Telecommunication Services", "subindustry": "Integrated Telecom", "peers": ["T", "TMUS", "CMCSA", "DIS", "NFLX"], "exposures": {"rates": 0.55, "credit": 0.70}},
    {"ticker": "TMUS", "name": "T-Mobile US, Inc.", "cik": "0001283699", "exchange": "NASDAQ", "sector": "Communication Services", "industry": "Telecommunication Services", "subindustry": "Wireless Telecom", "peers": ["T", "VZ", "CMCSA", "DIS", "NFLX"], "exposures": {"rates": 0.55, "credit": 0.60}},
    {"ticker": "AMD", "name": "Advanced Micro Devices, Inc.", "cik": "0000002488", "exchange": "NASDAQ", "sector": "Information Technology", "industry": "Semiconductors", "subindustry": "Semiconductors", "peers": ["NVDA", "AVGO", "QCOM", "INTC", "TXN"], "exposures": {"broad_usd": 0.75, "rates": 0.65}},
    {"ticker": "QCOM", "name": "QUALCOMM Incorporated", "cik": "0000804328", "exchange": "NASDAQ", "sector": "Information Technology", "industry": "Semiconductors", "subindustry": "Semiconductors", "peers": ["NVDA", "AMD", "AVGO", "INTC", "TXN"], "exposures": {"broad_usd": 0.75, "rates": 0.55}},
    {"ticker": "INTC", "name": "Intel Corporation", "cik": "0000050863", "exchange": "NASDAQ", "sector": "Information Technology", "industry": "Semiconductors", "subindustry": "Semiconductors", "peers": ["NVDA", "AMD", "AVGO", "QCOM", "TXN"], "exposures": {"broad_usd": 0.70, "rates": 0.55}},
    {"ticker": "TXN", "name": "Texas Instruments Incorporated", "cik": "0000097476", "exchange": "NASDAQ", "sector": "Information Technology", "industry": "Semiconductors", "subindustry": "Semiconductors", "peers": ["NVDA", "AMD", "AVGO", "QCOM", "INTC"], "exposures": {"broad_usd": 0.65, "rates": 0.45}},
    {"ticker": "MCD", "name": "McDonald's Corporation", "cik": "0000063908", "exchange": "NYSE", "sector": "Consumer Discretionary", "industry": "Hotels Restaurants & Leisure", "subindustry": "Restaurants", "peers": ["SBUX", "KO", "PEP", "WMT", "COST"], "exposures": {"broad_usd": 0.55, "inflation": 0.45}},
    {"ticker": "SBUX", "name": "Starbucks Corporation", "cik": "0000829224", "exchange": "NASDAQ", "sector": "Consumer Discretionary", "industry": "Hotels Restaurants & Leisure", "subindustry": "Restaurants", "peers": ["MCD", "KO", "PEP", "WMT", "COST"], "exposures": {"broad_usd": 0.45, "inflation": 0.45}},
    {"ticker": "LOW", "name": "Lowe's Companies, Inc.", "cik": "0000060667", "exchange": "NYSE", "sector": "Consumer Discretionary", "industry": "Specialty Retail", "subindustry": "Home Improvement Retail", "peers": ["HD", "WMT", "COST", "TGT", "AMZN"], "exposures": {"rates": 0.65, "mortgage": 0.75}},
    {"ticker": "TGT", "name": "Target Corporation", "cik": "0000027419", "exchange": "NYSE", "sector": "Consumer Staples", "industry": "Consumer Staples Distribution", "subindustry": "Discount Stores", "peers": ["WMT", "COST", "AMZN", "HD", "LOW"], "exposures": {"inflation": 0.45}},
    {"ticker": "COP", "name": "ConocoPhillips", "cik": "0001163165", "exchange": "NYSE", "sector": "Energy", "industry": "Oil Gas & Consumable Fuels", "subindustry": "Exploration & Production", "peers": ["XOM", "CVX", "SLB", "EOG", "MPC"], "exposures": {"wti": 1.0, "natural_gas": 0.75, "broad_usd": 0.45}},
    {"ticker": "SLB", "name": "Schlumberger Limited", "cik": "0000087347", "exchange": "NYSE", "sector": "Energy", "industry": "Energy Equipment & Services", "subindustry": "Oilfield Services", "peers": ["XOM", "CVX", "COP", "EOG", "MPC"], "exposures": {"wti": 0.70, "natural_gas": 0.55}},
    {"ticker": "EOG", "name": "EOG Resources, Inc.", "cik": "0000821189", "exchange": "NYSE", "sector": "Energy", "industry": "Oil Gas & Consumable Fuels", "subindustry": "Exploration & Production", "peers": ["XOM", "CVX", "COP", "SLB", "MPC"], "exposures": {"wti": 1.0, "natural_gas": 0.80}},
    {"ticker": "MPC", "name": "Marathon Petroleum Corporation", "cik": "0001510295", "exchange": "NYSE", "sector": "Energy", "industry": "Oil Gas & Consumable Fuels", "subindustry": "Refining & Marketing", "peers": ["XOM", "CVX", "COP", "SLB", "EOG"], "exposures": {"wti": 0.50, "natural_gas": 0.35}},
    {"ticker": "AMGN", "name": "Amgen Inc.", "cik": "0000318154", "exchange": "NASDAQ", "sector": "Health Care", "industry": "Biotechnology", "subindustry": "Biotechnology", "peers": ["LLY", "JNJ", "MRK", "PFE", "ABBV"], "exposures": {"regulatory": 0.80}},
    {"ticker": "PFE", "name": "Pfizer Inc.", "cik": "0000078003", "exchange": "NYSE", "sector": "Health Care", "industry": "Pharmaceuticals", "subindustry": "Pharmaceuticals", "peers": ["LLY", "JNJ", "MRK", "ABBV", "AMGN"], "exposures": {"regulatory": 0.75, "broad_usd": 0.55}}
  ]
}
